ytdl_gui/__init__.py
ytdl_gui/const.py
ytdl_gui/css/style.css
ytdl_gui/dialog.py
ytdl_gui/images/wall.png
ytdl_gui/main.py
ytdl_gui/youtube.py
ytdl_gui-0.1.5.dist-info/entry_points.txt
ytdl_gui-0.1.5.dist-info/WHEEL
ytdl_gui-0.1.5.dist-info/METADATA
ytdl_gui-0.1.5.dist-info/RECORD
